wisdom/__init__.py
wisdom/device.py
wisdom/errors.py
wisdom/utils.py
wisdom/datastream/EEGStream.py
wisdom/datastream/__init__.py
wisdom/preprocessing/__init__.py
wisdom/preprocessing/filter.py
wisdom/preprocessing/filter_utils.py
wisdom/visualization/__init__.py
wisdom/visualization/bandpower.py
wisdom/visualization/headplot.py
wisdom/visualization/psd.py
wisdom/visualization/spectogram.py
wisdom/visualization/timeseries1.py
wisdom/visualization/timeseries2.py
wisdom/visualization/vis.py
wisdom/wifiprovision/__init__.py
wisdom/wifiprovision/esp_prov.py
wisdom/wifiprovision/proto/__init__.py
wisdom/wifiprovision/proto/constants_pb2.py
wisdom/wifiprovision/proto/custom_config_pb2.py
wisdom/wifiprovision/proto/sec0_pb2.py
wisdom/wifiprovision/proto/sec1_pb2.py
wisdom/wifiprovision/proto/session_pb2.py
wisdom/wifiprovision/proto/wifi_config_pb2.py
wisdom/wifiprovision/proto/wifi_constants_pb2.py
wisdom/wifiprovision/proto/wifi_scan_pb2.py
wisdom/wifiprovision/prov/__init__.py
wisdom/wifiprovision/prov/custom_prov.py
wisdom/wifiprovision/prov/wifi_prov.py
wisdom/wifiprovision/security/__init__.py
wisdom/wifiprovision/security/security.py
wisdom/wifiprovision/security/security0.py
wisdom/wifiprovision/transport/__init__.py
wisdom/wifiprovision/transport/transport.py
wisdom/wifiprovision/transport/transport_http.py
wisdom/wifiprovision/utils/__init__.py
wisdom/wifiprovision/utils/convenience.py
wisdom_sdk-0.0.5.dist-info/LICENSE
wisdom_sdk-0.0.5.dist-info/METADATA
wisdom_sdk-0.0.5.dist-info/WHEEL
wisdom_sdk-0.0.5.dist-info/top_level.txt
wisdom_sdk-0.0.5.dist-info/RECORD
